LICENCE.rst
MANIFEST.in
README.rst
ez_setup.py
setup.py
COS/__init__.py
COS/_convolve.c
COS/_convolve.pyx
COS/coadd.py
COS/reduction.py
COS/spectrum.py
COS/utils.py
COS.egg-info/PKG-INFO
COS.egg-info/SOURCES.txt
COS.egg-info/dependency_links.txt
COS.egg-info/entry_points.txt
COS.egg-info/not-zip-safe
COS.egg-info/requires.txt
COS.egg-info/top_level.txt
COS/LSF/G130M.txt
COS/LSF/G140L.txt
COS/LSF/G160M.txt
COS/LSF/NUV.txt
COS/config/runcalcos.cfg
COS/config/runcalcos_specification.cfg