Metadata-Version: 1.1
Name: COS
Version: 0.1.0
Summary: Utilities for data taken with the Cosmic Origins Spectrograph on the Hubble Space Telescope
Home-page: https://github.com/cwfinn/COS
Author: Charles Finn
Author-email: c.w.finn2301@gmail.com
License: BSD
Download-URL: https://pypi.python.org/pypi/COS/0.1.0
Platform: UNKNOWN
Classifier: Intended Audience :: Science/Research
Classifier: License :: OSI Approved :: BSD License
Classifier: Operating System :: OS Independent
Classifier: Programming Language :: Cython
Classifier: Programming Language :: Python :: 2.6
Classifier: Programming Language :: Python :: 2.7
Classifier: Programming Language :: Python :: 3
Classifier: Topic :: Scientific/Engineering :: Astronomy
Classifier: Topic :: Scientific/Engineering :: Physics
Provides: COS
